pathfindwithinspace/__init__.py
pathfindwithinspace/pathfinder.py
pathfindwithinspace-0.0.0.8.dist-info/LICENSE.txt
pathfindwithinspace-0.0.0.8.dist-info/METADATA
pathfindwithinspace-0.0.0.8.dist-info/WHEEL
pathfindwithinspace-0.0.0.8.dist-info/top_level.txt
pathfindwithinspace-0.0.0.8.dist-info/RECORD
