Metadata-Version: 2.1
Name: pathfindwithinspace
Version: 0.0.0.8
Summary: This package help you to find path / files with your working package space
Home-page: https://github.com/avikdas29
Author: Avik Das
Author-email: avik_das_2017@cba.isb.edu
License: UNKNOWN
Project-URL: Bug Tracker, https://github.com/avikdas29
Platform: UNKNOWN
Classifier: Programming Language :: Python :: 3
Classifier: License :: OSI Approved :: MIT License
Classifier: Operating System :: OS Independent
Requires-Python: >=2.0
License-File: LICENSE.txt
